healthbip/__init__.py
healthbip/middleware.py
healthbip/urls.py
healthbip/views.py
healthbip-0.1.1.dist-info/LICENSE
healthbip-0.1.1.dist-info/WHEEL
healthbip-0.1.1.dist-info/METADATA
healthbip-0.1.1.dist-info/RECORD
