Metadata-Version: 2.1
Name: healthbip
Version: 0.1.1
Summary: Django Application Healthchecks
License: MIT
Author: Anders Innovations Oy
Author-email: admin@anders.fi
Requires-Python: >=3.6,<4.0
Classifier: License :: OSI Approved :: MIT License
Classifier: Programming Language :: Python :: 3
Classifier: Programming Language :: Python :: 3.6
Classifier: Programming Language :: Python :: 3.7
Requires-Dist: Django (>2)
